frida_runner.py
setup.py
frida_runner.egg-info/PKG-INFO
frida_runner.egg-info/SOURCES.txt
frida_runner.egg-info/dependency_links.txt
frida_runner.egg-info/entry_points.txt
frida_runner.egg-info/requires.txt
frida_runner.egg-info/top_level.txt