Metadata-Version: 1.0
Name: frida-runner
Version: 0.2.0
Summary: A Stupid CLI script to run Frida on iOS or Android
Home-page: https://github.com/appknox/frida-runner
Author: dhilipsiva
Author-email: dhilipsiva@gmail.com
License: UNKNOWN
Platform: UNKNOWN
